<config xmlns:xsi="http://www.w3.org/2001/XMLSchema-instance" xsi:noNamespaceSchemaLocation="urn:magento:module:MageSuite_Changelog:etc/changelog.xsd">
    <module
        id="MageSuite_Frontend"
        name="MageSuite_Frontend">
        <changelog>
            <tag version="3.0.0" date="2021-10-06">
                <entry>
                    <type>INIT</type>
                    <overview>Initial release</overview>
                    <description></description>
                </entry>
            </tag>
            <tag version="3.2.7" date="2022-06-30">
                <entry>
                    <type>FIX</type>
                    <overview>[IPET-1384] Allow setting redirection type for custom category URL</overview>
                </entry>
            </tag>
        </changelog>
    </module>
</config>
